butils/__init__.py
butils/case_converter.py
butils-0.0.6.dist-info/DESCRIPTION.rst
butils-0.0.6.dist-info/METADATA
butils-0.0.6.dist-info/RECORD
butils-0.0.6.dist-info/WHEEL
butils-0.0.6.dist-info/metadata.json
butils-0.0.6.dist-info/top_level.txt
