Metadata-Version: 2.0
Name: butils
Version: 0.0.6
Summary: A useful utils package
Home-page: UNKNOWN
Author: bohanzhang
Author-email: me@bohanzhang.com
License: MIT License
Keywords: utils
Platform: UNKNOWN
